audio_video_sync/__init__.py
audio_video_sync/cli.py
audio_video_sync/ffmpeg.py
audio_video_sync/sync.py
audio_video_sync-0.2.0.dist-info/METADATA
audio_video_sync-0.2.0.dist-info/WHEEL
audio_video_sync-0.2.0.dist-info/entry_points.txt
audio_video_sync-0.2.0.dist-info/licenses/LICENSE
audio_video_sync-0.2.0.dist-info/RECORD
