Metadata-Version: 2.4
Name: audio-video-sync
Version: 0.2.0
Summary: Auto-sync video with separately recorded audio using cross-correlation
Project-URL: Homepage, https://github.com/sanjeed5/audio-video-sync
Project-URL: Repository, https://github.com/sanjeed5/audio-video-sync
Author: Sanjeed
License: MIT
License-File: LICENSE
Keywords: audio,cover,ffmpeg,music,sync,video
Classifier: Development Status :: 4 - Beta
Classifier: Environment :: Console
Classifier: Intended Audience :: End Users/Desktop
Classifier: License :: OSI Approved :: MIT License
Classifier: Programming Language :: Python :: 3
Classifier: Programming Language :: Python :: 3.10
Classifier: Programming Language :: Python :: 3.11
Classifier: Programming Language :: Python :: 3.12
Classifier: Topic :: Multimedia :: Sound/Audio
Classifier: Topic :: Multimedia :: Video
Requires-Python: >=3.10
Requires-Dist: librosa>=0.10.0
Requires-Dist: loguru>=0.7.0
Requires-Dist: numpy>=1.24.0
Requires-Dist: scipy>=1.10.0
Requires-Dist: typer>=0.9.0
